bikram/__init__.py
bikram/bikram.py
bikram/constants.py
bikram-0.1.3.dist-info/DESCRIPTION.rst
bikram-0.1.3.dist-info/METADATA
bikram-0.1.3.dist-info/RECORD
bikram-0.1.3.dist-info/WHEEL
bikram-0.1.3.dist-info/metadata.json
bikram-0.1.3.dist-info/top_level.txt
