Metadata-Version: 2.0
Name: bikram
Version: 0.1.3
Summary: Utilities to work with Bikram/Vikram Samwat dates.
Home-page: https://github.com/poudel/bikram
Author: keshaB Paudel
Author-email: self@keshab.net
License: GNU General Public License v3
Keywords: bikram
Platform: UNKNOWN
Classifier: Development Status :: 2 - Pre-Alpha
Classifier: Intended Audience :: Developers
Classifier: License :: OSI Approved :: GNU General Public License v3 (GPLv3)
Classifier: Natural Language :: English
Classifier: Programming Language :: Python :: 2
Classifier: Programming Language :: Python :: 2.7
Classifier: Programming Language :: Python :: 3
Classifier: Programming Language :: Python :: 3.5
